esda/__init__.py
esda/adbscan.py
esda/correlogram.py
esda/crand.py
esda/gamma.py
esda/geary.py
esda/geary_local.py
esda/geary_local_mv.py
esda/getisord.py
esda/join_counts.py
esda/join_counts_local.py
esda/join_counts_local_bv.py
esda/join_counts_local_mv.py
esda/lee.py
esda/losh.py
esda/map_comparison.py
esda/mixture_smoothing.py
esda/moran.py
esda/moran_local_mv.py
esda/shape.py
esda/significance.py
esda/silhouettes.py
esda/smaup.py
esda/smoothing.py
esda/tabular.py
esda/topo.py
esda/util.py
esda/tests/__init__.py
esda/tests/regions.zip
esda/tests/test_adbscan.py
esda/tests/test_correlogram.py
esda/tests/test_crand.py
esda/tests/test_gamma.py
esda/tests/test_geary.py
esda/tests/test_getisord.py
esda/tests/test_join_counts.py
esda/tests/test_lee.py
esda/tests/test_ljc.py
esda/tests/test_ljc_bv.py
esda/tests/test_ljc_mv.py
esda/tests/test_local_geary.py
esda/tests/test_local_geary_mv.py
esda/tests/test_losh.py
esda/tests/test_map_comparison.py
esda/tests/test_mixture_smoothing.py
esda/tests/test_moran.py
esda/tests/test_moran_local_mv.py
esda/tests/test_shape.py
esda/tests/test_significance.py
esda/tests/test_silhouette.py
esda/tests/test_smaup.py
esda/tests/test_smoothing.py
esda/tests/test_topo.py
esda/tests/test_util.py
esda-2.8.1.dist-info/licenses/LICENSE.txt
esda-2.8.1.dist-info/METADATA
esda-2.8.1.dist-info/WHEEL
esda-2.8.1.dist-info/top_level.txt
esda-2.8.1.dist-info/RECORD
